caellion/__init__.py
caellion/pycommons/__init__.py
caellion/pycommons/codeanalysis/__init__.py
caellion/pycommons/codeanalysis/reports.py
caellion/pycommons/encoding/__init__.py
caellion/pycommons/encoding/base36.py
caellion/pycommons/encryption/__init__.py
caellion/pycommons/encryption/tripledes.py
caellion/pycommons/hashing/__init__.py
caellion/pycommons/hashing/file_hashing.py
caellion/pycommons/serializers/__init__.py
caellion/pycommons/serializers/datetime_serializer.py
caellion/pycommons/stringutil/__init__.py
caellion/pycommons/stringutil/formatters.py
caellion/pycommons/stringutil/unixpassword.py
tests/__init__.py
tests/test_codeanalysis_reports.py
tests/test_encoding_base36.py
tests/test_encryption_tripledes.py
tests/test_hashing_file_hashing.py
tests/test_serializers_datetime_serializer.py
tests/test_stringutil_formatters.py
tests/test_stringutil_unixpassword.py
caellion_python_commons-0.1.85.dist-info/LICENSE.txt
caellion_python_commons-0.1.85.dist-info/METADATA
caellion_python_commons-0.1.85.dist-info/WHEEL
caellion_python_commons-0.1.85.dist-info/top_level.txt
caellion_python_commons-0.1.85.dist-info/RECORD
