Metadata-Version: 2.1
Name: caellion-python-commons
Version: 0.1.85
Summary: Various utilities
Home-page: https://pypi.org/project/caellion-python-commons/
Author: Caellion
Author-email: administrator@michalpol.pl
License: Apache License 2.0
Platform: any
Classifier: Development Status :: 3 - Alpha
Classifier: Intended Audience :: Developers
Classifier: License :: OSI Approved :: Apache Software License
Classifier: Operating System :: OS Independent
Classifier: Programming Language :: Python
Classifier: Topic :: Software Development :: Libraries :: Python Modules
Requires-Python: >=3.7
License-File: LICENSE.txt
